zmlp/__init__.py
zmlp/client.py
zmlp/search.py
zmlp/training.py
zmlp/util.py
zmlp/app/__init__.py
zmlp/app/analysis_app.py
zmlp/app/asset_app.py
zmlp/app/clip_app.py
zmlp/app/datasource_app.py
zmlp/app/field_app.py
zmlp/app/job_app.py
zmlp/app/model_app.py
zmlp/app/pmod_app.py
zmlp/app/project_app.py
zmlp/app/zmlp_app.py
zmlp/entity/__init__.py
zmlp/entity/analysis.py
zmlp/entity/asset.py
zmlp/entity/base.py
zmlp/entity/clip.py
zmlp/entity/datasource.py
zmlp/entity/exception.py
zmlp/entity/field.py
zmlp/entity/job.py
zmlp/entity/model.py
zmlp/entity/pmod.py
zmlp/entity/project.py
zvi_client-1.1.3.dist-info/LICENSE.txt
zvi_client-1.1.3.dist-info/METADATA
zvi_client-1.1.3.dist-info/WHEEL
zvi_client-1.1.3.dist-info/top_level.txt
zvi_client-1.1.3.dist-info/RECORD
