Metadata-Version: 2.1
Name: zvi-client
Version: 1.1.3
Summary: Zorroa Visual Intelligence Python Client
Home-page: http://www.zorroa.com
Author: Matthew Chambers
Author-email: support@zorroa.com
License: Apache2
Keywords: machine learning artificial intelligence
Platform: UNKNOWN
Classifier: Programming Language :: Python :: 3
Classifier: Operating System :: OS Independent
Requires-Python: >=3.4
Requires-Dist: requests
Requires-Dist: pyOpenSSL
Requires-Dist: PyJWT (>=2.0)
Requires-Dist: backoff
Requires-Dist: pytest
